aws_test_harness/__init__.py
aws_test_harness/a_state_machine_execution_failure.py
aws_test_harness/a_thrown_exception.py
aws_test_harness/aws_resource_driver.py
aws_test_harness/aws_resource_mocking_engine.py
aws_test_harness/aws_test_double_driver.py
aws_test_harness/boto_session_factory.py
aws_test_harness/cloudformation_stack.py
aws_test_harness/dynamodb_table.py
aws_test_harness/exit_code.py
aws_test_harness/message_listener.py
aws_test_harness/s3_bucket.py
aws_test_harness/state_machine.py
aws_test_harness/state_machine_execution.py
aws_test_harness/task_context.py
aws_test_harness/test_resources_factory.py
aws_test_harness-0.1.1a7.dist-info/METADATA
aws_test_harness-0.1.1a7.dist-info/WHEEL
aws_test_harness-0.1.1a7.dist-info/RECORD
