Metadata-Version: 2.4
Name: aws-test-harness
Version: 0.1.1a7
Summary: Add your description here
Requires-Python: >=3.11
Requires-Dist: boto3-stubs-lite[cloudformation,dynamodb,s3,sqs,stepfunctions,sts]>=1.40.17
Requires-Dist: boto3>=1.40.17
